keywind_pfpc/__init__.py
keywind_pfpc/pfpc.py
keywind_pfpc-0.0.3.dist-info/LICENSE
keywind_pfpc-0.0.3.dist-info/METADATA
keywind_pfpc-0.0.3.dist-info/WHEEL
keywind_pfpc-0.0.3.dist-info/top_level.txt
keywind_pfpc-0.0.3.dist-info/RECORD
