Metadata-Version: 2.1
Name: keywind-pfpc
Version: 0.0.3
Summary: Installing this package will allow you to limit your input controls.
Home-page: https://github.com/keywind1207/keywind-pfpc
Author: Keywind
Author-email: keywind127@gmail.com
License: UNKNOWN
Project-URL: Bug Tracker, https://github.com/keywind1207/keywind-pfpc/issues
Platform: UNKNOWN
Classifier: Programming Language :: Python :: 3
Classifier: License :: OSI Approved :: MIT License
Classifier: Operating System :: OS Independent
Requires-Python: >=3.6
License-File: LICENSE
Requires-Dist: markdown
Requires-Dist: pynput
Requires-Dist: traitlets
